MANIFEST.in
setup.cfg
setup.py
d1_workspace/__init__.py
d1_workspace/cache_disk.py
d1_workspace/check_dependencies.py
d1_workspace/command_processor.py
d1_workspace/log_decorator.py
d1_workspace/query_engine_description.py
d1_workspace/settings.py
d1_workspace/t.py
d1_workspace/t2.py
d1_workspace/util.py
d1_workspace/workspace.py
d1_workspace/workspace_d1_client.py
d1_workspace/workspace_definition.py
d1_workspace/workspace_exception.py
d1_workspace/workspace_solr_client.py
d1_workspace/tests/test_cache_disk.py
d1_workspace/tests/test_command_processor.py
d1_workspace/tests/test_d1_client.py
d1_workspace/tests/test_query_engine_description.py
d1_workspace/tests/test_solr_client.py
d1_workspace/tests/test_util.py
d1_workspace/tests/test_workspace.py
d1_workspace/tests/workspace.xml
d1_workspace/tests/workspace_all.xml
d1_workspace/tests/workspace_empty.xml
d1_workspace/tests/workspace_single.xml
d1_workspace/tests/workspace_tiny_two_levels.xml
d1_workspace/types/__init__.py
d1_workspace/types/pyxbgen_all.py
d1_workspace/types/workspace_types.xsd
d1_workspace/types/generated/__init__.py
d1_workspace/types/generated/workspace_types.py
d1_workspace/types/generated/workspace_types_version.txt
dataone.workspace_client.egg-info/PKG-INFO
dataone.workspace_client.egg-info/SOURCES.txt
dataone.workspace_client.egg-info/dependency_links.txt
dataone.workspace_client.egg-info/requires.txt
dataone.workspace_client.egg-info/top_level.txt
examples/workspace.xml