Metadata-Version: 1.0
Name: dataone.workspace-client
Version: 0.0.6
Summary: A DataONE Workspace client library for Python
Home-page: http://dataone.org
Author: DataONE Project
Author-email: developers@dataone.org
License: Apache License, Version 2.0
Platform: UNKNOWN
